setup.py
global_identity/__init__.py
global_identity/global_identity.py
global_identity.egg-info/PKG-INFO
global_identity.egg-info/SOURCES.txt
global_identity.egg-info/dependency_links.txt
global_identity.egg-info/not-zip-safe
global_identity.egg-info/requires.txt
global_identity.egg-info/top_level.txt
tests/helpers/__init__.py
tests/helpers/my_helper.py
tests/unit/__init__.py
tests/unit/test_global_identity.py