Metadata-Version: 1.0
Name: global-identity
Version: 1.1.0
Summary: Global Identity Authentication PIP
Home-page: https://github.com/stone-payments/globalidentity-python
Author: mralves
Author-email: mralves@stone.com.br
License: MIT License
Keywords: global identity
Platform: UNKNOWN
